{
  "root": true,
  "project": {
    "name": "unorthodox-studio"
  },
  "api": {
    "projectId": "8rgjpxp9",
    "dataset": "production"
  },
  "plugins": [
    "@sanity/base",
    "@sanity/default-layout",
    "@sanity/default-login",
    "@sanity/desk-tool",
    "mux-input",
    "@sanity/orderable-document-list"
  ],
  "env": {
    "development": {
      "plugins": [
        "@sanity/vision"
      ]
    }
  },
  "parts": [
    {
      "name": "part:@sanity/base/schema",
      "path": "./schemas/schema"
    },
    {
      "name": "part:@sanity/desk-tool/structure",
      "path": "./deskStructure.js"
    }

  ]
}
